opcdiag/__init__.py
opcdiag/cli.py
opcdiag/controller.py
opcdiag/model.py
opcdiag/phys_pkg.py
opcdiag/presenter.py
opcdiag/py.typed
opcdiag/view.py
opc_diag-1.1.1.dist-info/LICENSE
opc_diag-1.1.1.dist-info/METADATA
opc_diag-1.1.1.dist-info/WHEEL
opc_diag-1.1.1.dist-info/entry_points.txt
opc_diag-1.1.1.dist-info/top_level.txt
opc_diag-1.1.1.dist-info/RECORD
