Metadata-Version: 2.1
Name: opc-diag
Version: 1.1.1
Summary: A command-line application for exploring Microsoft Word, Excel, and PowerPoint files from Office 2007 and later.
Author-email: Steve Canny <stcanny@gmail.com>
License: MIT
Project-URL: Changelog, https://github.com//opc-diag/blob/master/HISTORY.rst
Project-URL: Documentation, https://opc-diag.readthedocs.org/en/latest/
Project-URL: Homepage, https://github.com/python-openxml/opc-diag
Project-URL: Repository, https://github.com/python-openxml/opc-diag
Keywords: docx,pptx,xlsx,office,openxml,word,powerpoint,excel
Classifier: Development Status :: 5 - Production/Stable
Classifier: Environment :: Console
Classifier: Intended Audience :: Developers
Classifier: License :: OSI Approved :: MIT License
Classifier: Operating System :: OS Independent
Classifier: Programming Language :: Python
Classifier: Programming Language :: Python :: 3
Classifier: Programming Language :: Python :: 3.9
Classifier: Programming Language :: Python :: 3.10
Classifier: Programming Language :: Python :: 3.11
Classifier: Programming Language :: Python :: 3.12
Classifier: Topic :: Office/Business :: Office Suites
Classifier: Topic :: Software Development :: Libraries
Requires-Python: >=3.9
License-File: LICENSE
Requires-Dist: lxml >=4
